{"tblxXFBoztC0MiHCL" : {"table_name" : "Spain",
                        "field_ids"  : {"job_id"        : "fldK0dPjzrYTLbq8H",
                                        "title"         : "fldYT0MGMPE4crwM8",
                                        "group"         : "fldggbuSg3stp890n",
                                        "group_metrics" : "fldlflJWCQdQRlgwx",
                                        "company_name"  : "fldcFDIakt1GYcGZd",
                                        "location"      : "fldBITI7ca8oMiQ0e",
                                        "source"        : "fldvIt9No3oKkP9QN",
                                        "description"   : "fldULNjUV3l8uz5SV",
                                        "country"       : "fldMgNuIsBAKhRces",
                                        "date_posted"   : "fldgPkal466rDXzMy",
                                        "salary"        : "fldQk9V4K7n0UHysK",
                                        "salary_range"  : "fldBJ0MSVzRkTpr4b",
                                        "salary_avg"    : "fldUEWxP8YJwMkGLX",
                                        "contract_type" : "fldJygkANaRLHFENB",
                                        "experience"    : "fldrbSfRedShiqEtS",
                                        "remote_work"   : "fldE8kNQg8ef6OWkN",
                                        "tech_skills"   : "fldO98rLB9M3kQTnf"}},
 "tblZ7BhUSxLozThp3" : {"table_name" : "LATAM 001",
                        "field_ids"  : {"job_id"        : "fldC1hvxSFs3rVPhE",
                                        "title"         : "fldDDNNf8htERcNjR",
                                        "group"         : "fldZl3hnctSgp68m0",
                                        "group_metrics" : "fld7U1ILmMenTcffB",
                                        "company_name"  : "fldmG53TFTd70ncOo",
                                        "location"      : "fldwpOfa0yBWMDGo5",
                                        "source"        : "fldems3dVOfVFFmxR",
                                        "description"   : "fldKsFlu6eA8oCdiA",
                                        "country"       : "fldO6cCCt2O1Cy9Km",
                                        "date_posted"   : "fldagcwdLgg5REnoS",
                                        "salary"        : "fld87tdvYbWSfSvZf",
                                        "salary_range"  : "fld7yfvJgj2bWcUso",
                                        "salary_avg"    : "fldwzuAztwBQ9t1jA",
                                        "contract_type" : "fldzyXhtLyrMdydWS",
                                        "experience"    : "fldls8dxF91fr5o3T",
                                        "experience_levels" : "fldQPRAtykp7nGYOe",
                                        "remote_work"   : "fldChaVYkXhGPDfP6",
                                        "tech_skills"   : "fldGXGL2iXHtgc79s",
                                        "Especialidad"  : "fldka8JWaSAPGvlkk",
                                        "Perfil"        : "fldvIGxRDX72ydSWE"}},                  
 "tblWgZg2NsM5ociUW" : {"table_name" : "LATAM 002",
                        "field_ids"  : {"job_id"        : "fldAJqCNKWZByXl52",
                                        "title"         : "fldiwwUNhDKO1Ikfh",
                                        "group"         : "fldSR7hZqldnrtjty",
                                        "group_metrics" : "fldiyQN1WI2Ep0JWu",
                                        "company_name"  : "fldYxY8gTmocufrQB",
                                        "location"      : "fldGv6eimflZ2Hprz",
                                        "source"        : "fldWusXVxlnUKHupV",
                                        "description"   : "fldGudJQ8dEbpobTz",
                                        "country"       : "fldiW7kPbIfSzMjw4",
                                        "date_posted"   : "fldBJClPFOTPxx3QH",
                                        "salary"        : "fldJwESWgF2wOginv",
                                        "salary_range"  : "fldhJ1c4157Gihr5Q",
                                        "salary_avg"    : "fldDhgT2RWBsIn1OW",
                                        "contract_type" : "fldEPYF2kizL3cx4C",
                                        "experience"    : "fldlaz4yR3bLqXOWz",
                                        "experience_levels" : "fldHZAKqR6yFvBSRK",
                                        "remote_work"   : "fld5PEhRnV7lasWNC",
                                        "tech_skills"   : "fldJmtgweYgES4ZPi",
                                        "Especialidad"  : "fldQoiR7VgsIFw46c",
                                        "Perfil"        : "fldzlXcPrtIivONt3"}},
"tbl0qpV7gAUgTcEez" : {"table_name" : "LATAM 003",
                       "field_ids"  : {"job_id"        : "fldqLtX7y1Oj3Vpf5",
                                       "title"         : "fldX4ZcqZDfQiHIjp",
                                       "company_name"  : "fldA13q7vPCbUKOXI",
                                       "location"      : "fld1KiFhTuRXGmGX1",
                                       "source"        : "fld4vy6ohzeyHa8yR",
                                       "description"   : "fld9kzW59vH93Dua8",
                                       "country"       : "fldNQuiC3gIDygzzr",
                                       "date_posted"   : "fldWAaxtKao1lY4FY",
                                       "salary_min"    : "fld6LEIhqJHYBDKUy",
                                       "salary_max"    : "fldH71ggtB6rrhvqA",
                                       "salary_avg"    : "fldpan60gyCSOFmDg",
                                       "time_lapse"    : "fldHmazo2sKvaZRha",
                                       "salary_dollars_year" : "flde3oDdskqcQrYH7",
                                       "contract_type" : "fldnATtiEpvafDerF",
                                       "experience"    : "fldbtlZNRiCnvTnYe",
                                       "remote_work"   : "fld0A3IzvPG76fZIG",
                                       "tech_skills"   : "fld60y9SsJtyJZT8S",
                                       "experience_levels" : "fldbslC9X2oZNPlxi",
                                       "Especialidad"  : "fldQwUnfzE7yUhYCn",
                                       "Perfil"        : "fldcrob4H7byq7U6a"}},
"tbl6S7ztip0gcv241" : {"table_name" : "LATAM 000",
                       "field_ids"  : {"job_id"        : "fldOpA2WttGN9hR0k",
                                       "title"         : "fldGvHnwLDBTJo4tG",
                                       "company_name"  : "fldjwd8p6v46W3r9Q",
                                       "location"      : "fldanIL0AD99VUPtb",
                                       "source"        : "fldJc8q1va2LAyi9A",
                                       "description"   : "fldz5pG9paG0ZF5GE",
                                       "country"       : "fldVQAU34PKX2EvEN",
                                       "date_posted"   : "fldkwtppfHSSq8AI8",
                                       "salary_min"    : "fldRDgLQqsG2LlX84",
                                       "salary_max"    : "fldPuGFiGQqftMjHf",
                                       "salary_avg"    : "fldxA1tg4oRUJsGIY",
                                       "time_lapse"    : "fldQgTQbqG7Gmbybq",
                                       "salary_dollars_year" : "flde3oDdskqcQrYH7",
                                       "contract_type" : "fldJUw9pLgNxQStvA",
                                       "experience"    : "flduojBYTuU4zIf5B",
                                       "remote_work"   : "fldt2Q0rgrQr1Tn1u",
                                       "tech_skills"   : "fld7Bg7mFo5Rqei8P",
                                       "experience_levels" : "fldSoWvhicZwwNd7M",
                                       "Especialidad"  : "fldXjAOksOsuQr0gO",
                                       "Perfil"        : "fldB4PegiXBezLM4z",
                                       "currency"      : "fldcVZu2L7d07W7Ss",
                                       "chat_gpt"      : "fldmYVz9dynfMuBhF"}},
"tbl9tysdaaHUNLshO" : {"table_name" : "LATAM 000 purged",
                       "field_ids"  : {"job_id"        : "fldR01VGlenrKxhd7",
                                       "title"         : "fldJ68ggDoixkEuGt",
                                       "company_name"  : "fldm7E19YgLKxjRmD",
                                       "location"      : "flddY9EKsoQNwafGY",
                                       "source"        : "fldMNzjLnVJpbOImn",
                                       "description"   : "fldCGQzThVnEAVvTr",
                                       "country"       : "fldYr1NNWArBDUVRA",
                                       "date_posted"   : "fldkwtppfHSSq8AI8",
                                       "salary_min"    : "fldUeHEAidnGmBnlR",
                                       "salary_max"    : "fldS57y2yB7T42JU2",
                                       "salary_avg"    : "fldAbsm0W9yykI6VL",
                                       "time_lapse"    : "fldTRkJVirOkXrYod",
                                       "salary_dollars_year" : "flde3oDdskqcQrYH7",
                                       "contract_type" : "fldMvX29D1ubr8TIn",
                                       "experience"    : "fldxZKuILfBIaYFio",
                                       "remote_work"   : "fldwDhTb8cx5C9Neh",
                                       "tech_skills"   : "fldacH06x9Mv1uIlC",
                                       "experience_levels" : "fldVZno1aXGa73Dkz",
                                       "Especialidad"  : "fld0U1H4kz98rHqtB",
                                       "Perfil"        : "fldEFg70aIiSa1chm",
                                       "currency"      : "fldfwqnMDSUEIcx5f",
                                       "chat_gpt"      : "fldpzmsT5j4TnK1us"}}} 